{
  "type": "FeatureCollection",
  "features": [
    {
      "properties": {
        "status": "Under Control",
        "feedType": "incident",
        "sourceOrg": "NSW/RFS",
        "sourceId": "612956",
        "sourceFeed": "rfs-cap",
        "sourceTitle": "Wells Av, Thurgoona",
        "id": "2025-07-26T11:26:00.0000000:612956",
        "category1": "Other",
        "category2": "Other Non-Urgent Alerts",
        "name": "Wells Av, Thurgoona",
        "location": "13 Wells Av, Thurgoona 2640",
        "created": "2025-07-26T11:26:00+10:00",
        "updated": "2025-07-26T11:26:00+10:00",
        "webHeadline": "Unknown",
        "url": "https://www.rfs.nsw.gov.au/fire-information/fires-near-me",
        "sizeFmt": [
          "0 ha"
        ]
      },
      "type": "Feature",
      "geometry": {
        "type": "Point",
        "coordinates": [
          146.994171143,
          -36.04183197
        ]
      }
    },
    {
      "properties": {
        "status": "Under Control",
        "feedType": "incident",
        "sourceOrg": "NSW/RFS",
        "sourceId": "612931",
        "sourceFeed": "rfs-cap",
        "sourceTitle": "Urana Rd, Burrumbuttock",
        "id": "2025-07-26T01:42:00.0000000:612931",
        "category1": "Fire",
        "category2": "Bushfire",
        "name": "Urana Rd, Burrumbuttock",
        "location": "Urana Rd, Burrumbuttock 2642",
        "created": "2025-07-26T01:42:00+10:00",
        "updated": "2025-07-26T01:42:00+10:00",
        "webHeadline": "Unknown",
        "url": "https://www.rfs.nsw.gov.au/fire-information/fires-near-me",
        "sizeFmt": [
          "0 ha"
        ]
      },
      "type": "Feature",
      "geometry": {
        "type": "Point",
        "coordinates": [
          146.835998535,
          -35.878398896
        ]
      }
    },
    {
      "properties": {
        "status": "Under Control",
        "feedType": "incident",
        "sourceOrg": "NSW/RFS",
        "sourceId": "612909",
        "sourceFeed": "rfs-cap",
        "sourceTitle": "Towamba St, Towamba",
        "id": "2025-07-26T12:42:00.0000000:612909",
        "category1": "Other",
        "category2": "Other Non-Urgent Alerts",
        "name": "Towamba St, Towamba",
        "location": "4 Towamba St, Towamba 2550",
        "created": "2025-07-26T12:42:00+10:00",
        "updated": "2025-07-26T12:42:00+10:00",
        "webHeadline": "Unknown",
        "url": "https://www.rfs.nsw.gov.au/fire-information/fires-near-me",
        "sizeFmt": [
          "0 ha"
        ]
      },
      "type": "Feature",
      "geometry": {
        "type": "Point",
        "coordinates": [
          149.693450927,
          -37.085163117
        ]
      }
    },
    {
      "properties": {
        "status": "Safe",
        "cfaId": 230256,
        "feedType": "incident",
        "sourceOrg": "VIC/CFA",
        "sourceId": 230256,
        "sourceFeed": "cfa-incident",
        "sourceTitle": "",
        "eventId": 250720785,
        "id": "ESTA:250720785",
        "category1": "Fire",
        "category2": "Other",
        "created": "2025-07-26T17:12:00.000Z",
        "updated": "2025-07-26T17:44:00.000Z",
        "resources": 0,
        "location": "Rockbank",
        "size": "Small",
        "sizeFmt": "Small"
      },
      "type": "Feature",
      "geometry": {
        "type": "Point",
        "coordinates": [
          144.6365850479904,
          -37.71963554300088
        ]
      }
    },
    {
      "properties": {
        "status": "Safe",
        "cfaId": 230257,
        "feedType": "incident",
        "sourceOrg": "VIC/CFA",
        "sourceId": 230257,
        "sourceFeed": "cfa-incident",
        "sourceTitle": "Stud Rd",
        "eventId": 250720787,
        "id": "ESTA:250720787",
        "category1": "Other",
        "category2": "Other",
        "created": "2025-07-26T17:19:00.000Z",
        "updated": "2025-07-26T17:44:00.000Z",
        "resources": 0,
        "location": "Stud Rd, Rowville",
        "size": "Small",
        "sizeFmt": "Small"
      },
      "type": "Feature",
      "geometry": {
        "type": "Point",
        "coordinates": [
          145.2368585700575,
          -37.90626056820562
        ]
      }
    },
    {
      "properties": {
        "status": "Safe",
        "cfaId": 230258,
        "feedType": "incident",
        "sourceOrg": "VIC/CFA",
        "sourceId": 230258,
        "sourceFeed": "cfa-incident",
        "sourceTitle": "",
        "eventId": 250720791,
        "id": "ESTA:250720791",
        "category1": "Accident / Rescue",
        "category2": "Road Accident",
        "created": "2025-07-26T17:42:00.000Z",
        "updated": "2025-07-26T18:01:00.000Z",
        "resources": 0,
        "location": "Officer",
        "size": "Small",
        "sizeFmt": "Small"
      },
      "type": "Feature",
      "geometry": {
        "type": "Point",
        "coordinates": [
          145.43393330058248,
          -38.07952112105004
        ]
      }
    },
    {
      "properties": {
        "status": "Safe",
        "cfaId": 230259,
        "feedType": "incident",
        "sourceOrg": "VIC/CFA",
        "sourceId": 230259,
        "sourceFeed": "cfa-incident",
        "sourceTitle": "Carmody Ct",
        "eventId": 250720792,
        "id": "ESTA:250720792",
        "category1": "Fire",
        "category2": "Other",
        "created": "2025-07-26T17:45:00.000Z",
        "updated": "2025-07-26T18:03:00.000Z",
        "resources": 0,
        "location": "Carmody Ct, Cranbourne",
        "size": "Small",
        "sizeFmt": "Small"
      },
      "type": "Feature",
      "geometry": {
        "type": "Point",
        "coordinates": [
          145.2867202117782,
          -38.086469534926216
        ]
      }
    },
    {
      "properties": {
        "status": "Responding",
        "cfaId": 230261,
        "feedType": "incident",
        "sourceOrg": "VIC/CFA",
        "sourceId": 230261,
        "sourceFeed": "cfa-incident",
        "sourceTitle": "Pyke St",
        "eventId": 250720797,
        "id": "ESTA:250720797",
        "category1": "Fire",
        "category2": "Building Fire",
        "created": "2025-07-26T18:21:00.000Z",
        "updated": "2025-07-26T18:21:00.000Z",
        "resources": 3,
        "location": "Pyke St, Bundalong",
        "size": "Small",
        "sizeFmt": "Small"
      },
      "type": "Feature",
      "geometry": {
        "type": "Point",
        "coordinates": [
          146.16819091000957,
          -36.03674462047614
        ]
      }
    },
    {
      "properties": {
        "status": "Under Control",
        "mfbId": "250720786",
        "feedType": "incident",
        "sourceOrg": "VIC/FRV",
        "sourceId": "250720786",
        "sourceFeed": "mfb-incident",
        "sourceTitle": "Keilor Park",
        "id": "ESTA:250720786",
        "eventId": "250720786",
        "category1": "Other",
        "category2": "Other",
        "created": "2025-07-26T17:35:40.000Z",
        "updated": "2025-07-26T17:35:40.000Z",
        "resources": 1,
        "size": "Small",
        "sizeFmt": "Small",
        "location": "Keilor Park, Keilor Park"
      },
      "type": "Feature",
      "geometry": {
        "type": "Point",
        "coordinates": [
          144.86213556950125,
          -37.72605017209887
        ]
      }
    },
    {
      "properties": {
        "status": "Under Control",
        "mfbId": "250720796",
        "feedType": "incident",
        "sourceOrg": "VIC/FRV",
        "sourceId": "250720796",
        "sourceFeed": "mfb-incident",
        "sourceTitle": "Blackburn North",
        "id": "ESTA:250720796",
        "eventId": "250720796",
        "category1": "Other",
        "category2": "Other",
        "created": "2025-07-26T18:18:30.000Z",
        "updated": "2025-07-26T18:18:30.000Z",
        "resources": 1,
        "size": "Small",
        "sizeFmt": "Small",
        "location": "Blackburn North, Blackburn North"
      },
      "type": "Feature",
      "geometry": {
        "type": "Point",
        "coordinates": [
          145.15972382830668,
          -37.80093418603903
        ]
      }
    },
    {
      "properties": {
        "status": "Request For Assistance",
        "sesId": 573432,
        "feedType": "incident",
        "sourceOrg": "VIC/SES",
        "sourceId": 573432,
        "sourceFeed": "ses-incident",
        "sourceTitle": "Undefined",
        "eventId": 250752449,
        "id": "ESTA:250752449",
        "category1": "Building Damage",
        "category2": "Building Damage",
        "created": "2025-07-26T00:38:00.000Z",
        "updated": "2025-07-26T05:52:00.000Z",
        "resources": 1,
        "location": "Kinglake"
      },
      "type": "Feature",
      "geometry": {
        "type": "Point",
        "coordinates": [
          145.35822877209284,
          -37.52606230916093
        ]
      }
    },
    {
      "properties": {
        "status": "Request For Assistance",
        "sesId": 573572,
        "feedType": "incident",
        "sourceOrg": "VIC/SES",
        "sourceId": 573572,
        "sourceFeed": "ses-incident",
        "sourceTitle": "Undefined",
        "eventId": 250752582,
        "id": "ESTA:250752582",
        "category1": "Flooding",
        "category2": "Flooding",
        "created": "2025-07-26T09:49:00.000Z",
        "updated": "2025-07-26T09:52:00.000Z",
        "resources": 0,
        "location": "Kinglake Central"
      },
      "type": "Feature",
      "geometry": {
        "type": "Point",
        "coordinates": [
          145.32568691592965,
          -37.52489333604045
        ]
      }
    }
  ],
  "properties": {
    "conditions": {
      "fdr": {
        "Mallee": "NO FORECAST",
        "Wimmera": "NO FORECAST",
        "South West": "NO FORECAST",
        "Northern Country": "NO FORECAST",
        "North Central": "NO FORECAST",
        "Central": "NO FORECAST",
        "North East": "NO FORECAST",
        "West and South Gippsland": "NO FORECAST",
        "East Gippsland": "NO FORECAST"
      },
      "tfb": {
        "East Gippsland": "NO - RESTRICTIONS MAY APPLY",
        "West and South Gippsland": "NO - RESTRICTIONS MAY APPLY",
        "North East": "NO - RESTRICTIONS MAY APPLY",
        "Central": "NO - RESTRICTIONS MAY APPLY",
        "North Central": "NO - RESTRICTIONS MAY APPLY",
        "Northern Country": "NO - RESTRICTIONS MAY APPLY",
        "South West": "NO - RESTRICTIONS MAY APPLY",
        "Wimmera": "NO - RESTRICTIONS MAY APPLY",
        "Mallee": "NO - RESTRICTIONS MAY APPLY"
      },
      "forecasts": [
        {
          "fdr": {
            "Mallee": "NO FORECAST",
            "Wimmera": "NO FORECAST",
            "South West": "NO FORECAST",
            "Northern Country": "NO FORECAST",
            "North Central": "NO FORECAST",
            "Central": "NO FORECAST",
            "North East": "NO FORECAST",
            "West and South Gippsland": "NO FORECAST",
            "East Gippsland": "NO FORECAST"
          },
          "tfb": {
            "East Gippsland": "NO - RESTRICTIONS MAY APPLY",
            "West and South Gippsland": "NO - RESTRICTIONS MAY APPLY",
            "North East": "NO - RESTRICTIONS MAY APPLY",
            "Central": "NO - RESTRICTIONS MAY APPLY",
            "North Central": "NO - RESTRICTIONS MAY APPLY",
            "Northern Country": "NO - RESTRICTIONS MAY APPLY",
            "South West": "NO - RESTRICTIONS MAY APPLY",
            "Wimmera": "NO - RESTRICTIONS MAY APPLY",
            "Mallee": "NO - RESTRICTIONS MAY APPLY"
          },
          "date": "2025-07-26T14:00:00.000Z",
          "heat": {
            "Mallee": "Not Declared",
            "Wimmera": "Not Declared",
            "Northern Country": "Not Declared",
            "North East": "Not Declared",
            "East Gippsland": "Not Declared",
            "West and South Gippsland": "Not Declared",
            "Central": "Not Declared",
            "North Central": "Not Declared",
            "South West": "Not Declared"
          },
          "asthma": {
            "Mallee": "None",
            "Wimmera": "None",
            "Northern Country": "None",
            "North East": "None",
            "East Gippsland": "None",
            "West and South Gippsland": "None",
            "Central": "None",
            "North Central": "None",
            "South West": "None"
          }
        },
        {
          "fdr": {
            "Mallee": "NO FORECAST",
            "Wimmera": "NO FORECAST",
            "South West": "NO FORECAST",
            "Northern Country": "NO FORECAST",
            "North Central": "NO FORECAST",
            "Central": "NO FORECAST",
            "North East": "NO FORECAST",
            "West and South Gippsland": "NO FORECAST",
            "East Gippsland": "NO FORECAST"
          },
          "tfb": {
            "East Gippsland": "NO - RESTRICTIONS MAY APPLY",
            "West and South Gippsland": "NO - RESTRICTIONS MAY APPLY",
            "North East": "NO - RESTRICTIONS MAY APPLY",
            "Central": "NO - RESTRICTIONS MAY APPLY",
            "North Central": "NO - RESTRICTIONS MAY APPLY",
            "Northern Country": "NO - RESTRICTIONS MAY APPLY",
            "South West": "NO - RESTRICTIONS MAY APPLY",
            "Wimmera": "NO - RESTRICTIONS MAY APPLY",
            "Mallee": "NO - RESTRICTIONS MAY APPLY"
          },
          "date": "2025-07-27T14:00:00.000Z",
          "heat": {
            "Mallee": "Not Declared",
            "Wimmera": "Not Declared",
            "Northern Country": "Not Declared",
            "North East": "Not Declared",
            "East Gippsland": "Not Declared",
            "West and South Gippsland": "Not Declared",
            "Central": "Not Declared",
            "North Central": "Not Declared",
            "South West": "Not Declared"
          },
          "asthma": {
            "Mallee": "None",
            "Wimmera": "None",
            "Northern Country": "None",
            "North East": "None",
            "East Gippsland": "None",
            "West and South Gippsland": "None",
            "Central": "None",
            "North Central": "None",
            "South West": "None"
          }
        },
        {
          "fdr": {
            "Mallee": "NO FORECAST",
            "Wimmera": "NO FORECAST",
            "South West": "NO FORECAST",
            "Northern Country": "NO FORECAST",
            "North Central": "NO FORECAST",
            "Central": "NO FORECAST",
            "North East": "NO FORECAST",
            "West and South Gippsland": "NO FORECAST",
            "East Gippsland": "NO FORECAST"
          },
          "tfb": {
            "East Gippsland": "NO - RESTRICTIONS MAY APPLY",
            "West and South Gippsland": "NO - RESTRICTIONS MAY APPLY",
            "North East": "NO - RESTRICTIONS MAY APPLY",
            "Central": "NO - RESTRICTIONS MAY APPLY",
            "North Central": "NO - RESTRICTIONS MAY APPLY",
            "Northern Country": "NO - RESTRICTIONS MAY APPLY",
            "South West": "NO - RESTRICTIONS MAY APPLY",
            "Wimmera": "NO - RESTRICTIONS MAY APPLY",
            "Mallee": "NO - RESTRICTIONS MAY APPLY"
          },
          "date": "2025-07-28T14:00:00.000Z",
          "heat": {
            "Mallee": "Not Declared",
            "Wimmera": "Not Declared",
            "Northern Country": "Not Declared",
            "North East": "Not Declared",
            "East Gippsland": "Not Declared",
            "West and South Gippsland": "Not Declared",
            "Central": "Not Declared",
            "North Central": "Not Declared",
            "South West": "Not Declared"
          },
          "asthma": {
            "Mallee": "None",
            "Wimmera": "None",
            "Northern Country": "None",
            "North East": "None",
            "East Gippsland": "None",
            "West and South Gippsland": "None",
            "Central": "None",
            "North Central": "None",
            "South West": "None"
          }
        },
        {
          "fdr": {
            "Mallee": "NO FORECAST",
            "Wimmera": "NO FORECAST",
            "South West": "NO FORECAST",
            "Northern Country": "NO FORECAST",
            "North Central": "NO FORECAST",
            "Central": "NO FORECAST",
            "North East": "NO FORECAST",
            "West and South Gippsland": "NO FORECAST",
            "East Gippsland": "NO FORECAST"
          },
          "tfb": {
            "East Gippsland": "NO - RESTRICTIONS MAY APPLY",
            "West and South Gippsland": "NO - RESTRICTIONS MAY APPLY",
            "North East": "NO - RESTRICTIONS MAY APPLY",
            "Central": "NO - RESTRICTIONS MAY APPLY",
            "North Central": "NO - RESTRICTIONS MAY APPLY",
            "Northern Country": "NO - RESTRICTIONS MAY APPLY",
            "South West": "NO - RESTRICTIONS MAY APPLY",
            "Wimmera": "NO - RESTRICTIONS MAY APPLY",
            "Mallee": "NO - RESTRICTIONS MAY APPLY"
          },
          "date": "2025-07-29T14:00:00.000Z",
          "heat": {
            "Mallee": "Not Declared",
            "Wimmera": "Not Declared",
            "Northern Country": "Not Declared",
            "North East": "Not Declared",
            "East Gippsland": "Not Declared",
            "West and South Gippsland": "Not Declared",
            "Central": "Not Declared",
            "North Central": "Not Declared",
            "South West": "Not Declared"
          }
        }
      ],
      "heat": {
        "Mallee": "Not Declared",
        "Wimmera": "Not Declared",
        "Northern Country": "Not Declared",
        "North East": "Not Declared",
        "East Gippsland": "Not Declared",
        "West and South Gippsland": "Not Declared",
        "Central": "Not Declared",
        "North Central": "Not Declared",
        "South West": "Not Declared"
      },
      "asthma": {
        "Mallee": "None",
        "Wimmera": "None",
        "Northern Country": "None",
        "North East": "None",
        "East Gippsland": "None",
        "West and South Gippsland": "None",
        "Central": "None",
        "North Central": "None",
        "South West": "None"
      }
    },
    "notices": [],
    "lastUpdated": "2025-07-26T18:38:19.917Z",
    "featureCount": 12
  }
}
