{
  "type": "FeatureCollection",
  "features": [
    {
      "properties": {
        "status": "Patrolled",
        "feedType": "incident",
        "sourceOrg": "VIC/DELWP",
        "sourceId": 3006871,
        "sourceFeed": "delwp-burns",
        "sourceTitle": "Tonimbuk - Dingo Ridge Track ",
        "id": 3006871,
        "category1": "Planned Burn",
        "category2": "Planned Burn",
        "created": "2025-08-11T07:49:54.000Z",
        "updated": "2025-08-11T07:49:54.000Z",
        "resources": 0,
        "size": "84.61",
        "sizeFmt": "84.61 Ha.",
        "url": "https://www.ffm.vic.gov.au/bushfire-fuel-and-risk-management/planned-burning-in-victoria",
        "location": "2.1Km W Of Tonimbuk"
      },
      "type": "Feature",
      "geometry": {
        "type": "Point",
        "coordinates": [
          145.6878541,
          -38.0039995
        ]
      }
    },
    {
      "properties": {
        "status": "Patrolled",
        "feedType": "incident",
        "sourceOrg": "VIC/DELWP",
        "sourceId": 3010880,
        "sourceFeed": "delwp-burns",
        "sourceTitle": "Mooroopna - Common Track",
        "id": 3010880,
        "category1": "Planned Burn",
        "category2": "Planned Burn",
        "created": "2025-08-15T05:56:32.000Z",
        "updated": "2025-08-15T05:56:32.000Z",
        "resources": 0,
        "size": "2.36",
        "sizeFmt": "2.36 Ha.",
        "url": "https://www.ffm.vic.gov.au/bushfire-fuel-and-risk-management/planned-burning-in-victoria",
        "location": "1.2Km S Of Mooroopna"
      },
      "type": "Feature",
      "geometry": {
        "type": "Point",
        "coordinates": [
          145.3626601,
          -36.4009307
        ]
      }
    },
    {
      "properties": {
        "status": "Responding",
        "estaId": 120728473,
        "feedType": "incident",
        "source": "000",
        "sourceOrg": "VIC/FRV",
        "sourceId": "250819168",
        "sourceFeed": "mfb-incident",
        "sourceTitle": "England St",
        "eventId": "250819168",
        "id": "ESTA:250819168",
        "suppress": false,
        "category1": "Fire",
        "category2": "Non Structure Fire",
        "created": "2025-08-17T14:34:02.000Z",
        "updated": "2025-08-17T14:34:02.000Z",
        "resources": 2,
        "location": "England St, Dandenong South",
        "cfaId": 232861,
        "size": "Small",
        "sizeFmt": "Small",
        "mfbId": "250819168"
      },
      "type": "Feature",
      "geometry": {
        "type": "Point",
        "coordinates": [
          145.21891588188242,
          -38.030965593475145
        ]
      }
    },
    {
      "properties": {
        "status": "Responding",
        "estaId": 120728511,
        "feedType": "incident",
        "source": "000",
        "sourceOrg": "VIC/FRV",
        "sourceId": "250819169",
        "sourceFeed": "mfb-incident",
        "sourceTitle": "Berry Ct",
        "eventId": "250819169",
        "id": "ESTA:250819169",
        "suppress": false,
        "category1": "Hazardous Material",
        "category2": "Hazardous Material",
        "created": "2025-08-17T14:37:41.000Z",
        "updated": "2025-08-17T14:37:41.000Z",
        "resources": 0,
        "location": "Berry Ct, Doveton",
        "cfaId": 232862,
        "size": "Small",
        "sizeFmt": "Small",
        "mfbId": "250819169"
      },
      "type": "Feature",
      "geometry": {
        "type": "Point",
        "coordinates": [
          145.2370755118696,
          -37.98518202855666
        ]
      }
    },
    {
      "properties": {
        "status": "Responding",
        "estaId": 120728516,
        "feedType": "incident",
        "source": "000",
        "sourceOrg": "VIC/CFA",
        "sourceId": 232863,
        "sourceFeed": "cfa-incident",
        "sourceTitle": "",
        "eventId": 250819170,
        "id": "ESTA:250819170",
        "suppress": false,
        "category1": "Fire",
        "category2": "Other",
        "created": "2025-08-17T14:38:00.000Z",
        "updated": "2025-08-17T14:38:00.000Z",
        "resources": 0,
        "location": "California Gully",
        "cfaId": 232863,
        "size": "Small",
        "sizeFmt": "Small"
      },
      "type": "Feature",
      "geometry": {
        "type": "Point",
        "coordinates": [
          144.26967408867145,
          -36.720971683289
        ]
      }
    },
    {
      "properties": {
        "status": "Responding",
        "estaId": 120728519,
        "feedType": "incident",
        "source": "000",
        "sourceOrg": "VIC/CFA",
        "sourceId": 232864,
        "sourceFeed": "cfa-incident",
        "sourceTitle": "Sunbury Rd",
        "eventId": 250819172,
        "id": "ESTA:250819172",
        "suppress": false,
        "category1": "Accident / Rescue",
        "category2": "Road Accident",
        "created": "2025-08-17T14:39:00.000Z",
        "updated": "2025-08-17T14:39:00.000Z",
        "resources": 0,
        "location": "Sunbury Rd, Melbourne Airport",
        "cfaId": 232864,
        "size": "Small",
        "sizeFmt": "Small"
      },
      "type": "Feature",
      "geometry": {
        "type": "Point",
        "coordinates": [
          144.84672966501634,
          -37.65776914737244
        ]
      }
    },
    {
      "properties": {
        "status": "Safe",
        "cfaId": 232859,
        "feedType": "incident",
        "sourceOrg": "VIC/FRV",
        "sourceId": "250819161",
        "sourceFeed": "mfb-incident",
        "sourceTitle": "Springside Dr",
        "eventId": "250819161",
        "id": "ESTA:250819161",
        "category1": "Fire",
        "category2": "Non Structure Fire",
        "created": "2025-08-17T14:21:56.000Z",
        "updated": "2025-08-17T14:21:56.000Z",
        "resources": 1,
        "location": "Springside Dr, Cranbourne West",
        "size": "Small",
        "sizeFmt": "Small",
        "mfbId": "250819161"
      },
      "type": "Feature",
      "geometry": {
        "type": "Point",
        "coordinates": [
          145.24666783603263,
          -38.09533562578632
        ]
      }
    },
    {
      "properties": {
        "status": "Request For Assistance",
        "sesId": 574582,
        "feedType": "incident",
        "sourceOrg": "VIC/SES",
        "sourceId": 574582,
        "sourceFeed": "ses-incident",
        "sourceTitle": "Undefined",
        "eventId": 250850692,
        "id": "ESTA:250850692",
        "category1": "Flooding",
        "category2": "Flooding",
        "created": "2025-08-17T14:04:40.000Z",
        "updated": "2025-08-17T14:28:21.000Z",
        "resources": 1,
        "location": "Lorne"
      },
      "type": "Feature",
      "geometry": {
        "type": "Point",
        "coordinates": [
          143.9705894295652,
          -38.53385657839324
        ]
      }
    }
  ],
  "properties": {
    "conditions": {
      "fdr": {
        "Mallee": "NO FORECAST",
        "Wimmera": "NO FORECAST",
        "South West": "NO FORECAST",
        "Northern Country": "NO FORECAST",
        "North Central": "NO FORECAST",
        "Central": "NO FORECAST",
        "North East": "NO FORECAST",
        "West and South Gippsland": "NO FORECAST",
        "East Gippsland": "NO FORECAST"
      },
      "tfb": {
        "East Gippsland": "NO - RESTRICTIONS MAY APPLY",
        "West and South Gippsland": "NO - RESTRICTIONS MAY APPLY",
        "North East": "NO - RESTRICTIONS MAY APPLY",
        "Central": "NO - RESTRICTIONS MAY APPLY",
        "North Central": "NO - RESTRICTIONS MAY APPLY",
        "Northern Country": "NO - RESTRICTIONS MAY APPLY",
        "South West": "NO - RESTRICTIONS MAY APPLY",
        "Wimmera": "NO - RESTRICTIONS MAY APPLY",
        "Mallee": "NO - RESTRICTIONS MAY APPLY"
      },
      "forecasts": [
        {
          "fdr": {
            "Mallee": "NO FORECAST",
            "Wimmera": "NO FORECAST",
            "South West": "NO FORECAST",
            "Northern Country": "NO FORECAST",
            "North Central": "NO FORECAST",
            "Central": "NO FORECAST",
            "North East": "NO FORECAST",
            "West and South Gippsland": "NO FORECAST",
            "East Gippsland": "NO FORECAST"
          },
          "tfb": {
            "East Gippsland": "NO - RESTRICTIONS MAY APPLY",
            "West and South Gippsland": "NO - RESTRICTIONS MAY APPLY",
            "North East": "NO - RESTRICTIONS MAY APPLY",
            "Central": "NO - RESTRICTIONS MAY APPLY",
            "North Central": "NO - RESTRICTIONS MAY APPLY",
            "Northern Country": "NO - RESTRICTIONS MAY APPLY",
            "South West": "NO - RESTRICTIONS MAY APPLY",
            "Wimmera": "NO - RESTRICTIONS MAY APPLY",
            "Mallee": "NO - RESTRICTIONS MAY APPLY"
          },
          "date": "2025-08-17T14:00:00.000Z",
          "heat": {
            "Mallee": "Not Declared",
            "Wimmera": "Not Declared",
            "Northern Country": "Not Declared",
            "North East": "Not Declared",
            "East Gippsland": "Not Declared",
            "West and South Gippsland": "Not Declared",
            "Central": "Not Declared",
            "North Central": "Not Declared",
            "South West": "Not Declared"
          },
          "asthma": {
            "Mallee": "None",
            "Wimmera": "None",
            "Northern Country": "None",
            "North East": "None",
            "East Gippsland": "None",
            "West and South Gippsland": "None",
            "Central": "None",
            "North Central": "None",
            "South West": "None"
          }
        },
        {
          "fdr": {
            "Mallee": "NO FORECAST",
            "Wimmera": "NO FORECAST",
            "South West": "NO FORECAST",
            "Northern Country": "NO FORECAST",
            "North Central": "NO FORECAST",
            "Central": "NO FORECAST",
            "North East": "NO FORECAST",
            "West and South Gippsland": "NO FORECAST",
            "East Gippsland": "NO FORECAST"
          },
          "tfb": {
            "East Gippsland": "NO - RESTRICTIONS MAY APPLY",
            "West and South Gippsland": "NO - RESTRICTIONS MAY APPLY",
            "North East": "NO - RESTRICTIONS MAY APPLY",
            "Central": "NO - RESTRICTIONS MAY APPLY",
            "North Central": "NO - RESTRICTIONS MAY APPLY",
            "Northern Country": "NO - RESTRICTIONS MAY APPLY",
            "South West": "NO - RESTRICTIONS MAY APPLY",
            "Wimmera": "NO - RESTRICTIONS MAY APPLY",
            "Mallee": "NO - RESTRICTIONS MAY APPLY"
          },
          "date": "2025-08-18T14:00:00.000Z",
          "heat": {
            "Mallee": "Not Declared",
            "Wimmera": "Not Declared",
            "Northern Country": "Not Declared",
            "North East": "Not Declared",
            "East Gippsland": "Not Declared",
            "West and South Gippsland": "Not Declared",
            "Central": "Not Declared",
            "North Central": "Not Declared",
            "South West": "Not Declared"
          },
          "asthma": {
            "Mallee": "None",
            "Wimmera": "None",
            "Northern Country": "None",
            "North East": "None",
            "East Gippsland": "None",
            "West and South Gippsland": "None",
            "Central": "None",
            "North Central": "None",
            "South West": "None"
          }
        },
        {
          "fdr": {
            "Mallee": "NO FORECAST",
            "Wimmera": "NO FORECAST",
            "South West": "NO FORECAST",
            "Northern Country": "NO FORECAST",
            "North Central": "NO FORECAST",
            "Central": "NO FORECAST",
            "North East": "NO FORECAST",
            "West and South Gippsland": "NO FORECAST",
            "East Gippsland": "NO FORECAST"
          },
          "tfb": {
            "East Gippsland": "NO - RESTRICTIONS MAY APPLY",
            "West and South Gippsland": "NO - RESTRICTIONS MAY APPLY",
            "North East": "NO - RESTRICTIONS MAY APPLY",
            "Central": "NO - RESTRICTIONS MAY APPLY",
            "North Central": "NO - RESTRICTIONS MAY APPLY",
            "Northern Country": "NO - RESTRICTIONS MAY APPLY",
            "South West": "NO - RESTRICTIONS MAY APPLY",
            "Wimmera": "NO - RESTRICTIONS MAY APPLY",
            "Mallee": "NO - RESTRICTIONS MAY APPLY"
          },
          "date": "2025-08-19T14:00:00.000Z",
          "heat": {
            "Mallee": "Not Declared",
            "Wimmera": "Not Declared",
            "Northern Country": "Not Declared",
            "North East": "Not Declared",
            "East Gippsland": "Not Declared",
            "West and South Gippsland": "Not Declared",
            "Central": "Not Declared",
            "North Central": "Not Declared",
            "South West": "Not Declared"
          },
          "asthma": {
            "Mallee": "None",
            "Wimmera": "None",
            "Northern Country": "None",
            "North East": "None",
            "East Gippsland": "None",
            "West and South Gippsland": "None",
            "Central": "None",
            "North Central": "None",
            "South West": "None"
          }
        },
        {
          "fdr": {
            "Mallee": "NO FORECAST",
            "Wimmera": "NO FORECAST",
            "South West": "NO FORECAST",
            "Northern Country": "NO FORECAST",
            "North Central": "NO FORECAST",
            "Central": "NO FORECAST",
            "North East": "NO FORECAST",
            "West and South Gippsland": "NO FORECAST",
            "East Gippsland": "NO FORECAST"
          },
          "tfb": {
            "East Gippsland": "NO - RESTRICTIONS MAY APPLY",
            "West and South Gippsland": "NO - RESTRICTIONS MAY APPLY",
            "North East": "NO - RESTRICTIONS MAY APPLY",
            "Central": "NO - RESTRICTIONS MAY APPLY",
            "North Central": "NO - RESTRICTIONS MAY APPLY",
            "Northern Country": "NO - RESTRICTIONS MAY APPLY",
            "South West": "NO - RESTRICTIONS MAY APPLY",
            "Wimmera": "NO - RESTRICTIONS MAY APPLY",
            "Mallee": "NO - RESTRICTIONS MAY APPLY"
          },
          "date": "2025-08-20T14:00:00.000Z",
          "heat": {
            "Mallee": "Not Declared",
            "Wimmera": "Not Declared",
            "Northern Country": "Not Declared",
            "North East": "Not Declared",
            "East Gippsland": "Not Declared",
            "West and South Gippsland": "Not Declared",
            "Central": "Not Declared",
            "North Central": "Not Declared",
            "South West": "Not Declared"
          }
        }
      ],
      "heat": {
        "Mallee": "Not Declared",
        "Wimmera": "Not Declared",
        "Northern Country": "Not Declared",
        "North East": "Not Declared",
        "East Gippsland": "Not Declared",
        "West and South Gippsland": "Not Declared",
        "Central": "Not Declared",
        "North Central": "Not Declared",
        "South West": "Not Declared"
      },
      "asthma": {
        "Mallee": "None",
        "Wimmera": "None",
        "Northern Country": "None",
        "North East": "None",
        "East Gippsland": "None",
        "West and South Gippsland": "None",
        "Central": "None",
        "North Central": "None",
        "South West": "None"
      }
    },
    "notices": [],
    "lastUpdated": "2025-08-17T14:40:20.296Z",
    "featureCount": 10
  }
}
