{
  "type": "FeatureCollection",
  "features": [
    {
      "properties": {
        "status": "Under Control",
        "feedType": "incident",
        "sourceOrg": "VIC/DELWP",
        "sourceId": 1005999,
        "sourceFeed": "delwp-incident",
        "sourceTitle": "Far South West 51 - Dergholm - Vickerys Rd",
        "id": 1005999,
        "category1": "Fire",
        "category2": "Bushfire",
        "created": "2025-03-12T02:08:00.000Z",
        "updated": "2025-05-26T04:26:00.000Z",
        "resources": 0,
        "size": "1054.00",
        "sizeFmt": "1054.00 Ha.",
        "location": "9Km Sw Of Dergholm"
      },
      "type": "Feature",
      "geometry": {
        "type": "Point",
        "coordinates": [
          141.1356,
          -37.4202
        ]
      }
    },
    {
      "properties": {
        "status": "Patrolled",
        "feedType": "incident",
        "sourceOrg": "VIC/DELWP",
        "sourceId": 3006178,
        "sourceFeed": "delwp-burns",
        "sourceTitle": "Canadian - Sparrow Reserve",
        "id": 3006178,
        "category1": "Planned Burn",
        "category2": "Planned Burn",
        "created": "2025-06-20T04:13:44.000Z",
        "updated": "2025-06-20T04:13:44.000Z",
        "resources": 0,
        "size": "0.30",
        "sizeFmt": "0.30 Ha.",
        "url": "https://www.ffm.vic.gov.au/bushfire-fuel-and-risk-management/planned-burning-in-victoria",
        "location": "2Km Se Of Ballarat"
      },
      "type": "Feature",
      "geometry": {
        "type": "Point",
        "coordinates": [
          143.8845782,
          -37.5779636
        ]
      }
    },
    {
      "properties": {
        "status": "Patrolled",
        "feedType": "incident",
        "sourceOrg": "VIC/DELWP",
        "sourceId": 3007356,
        "sourceFeed": "delwp-burns",
        "sourceTitle": "Morwell - Crinigan Bushland Reserve 2",
        "id": 3007356,
        "category1": "Planned Burn",
        "category2": "Planned Burn",
        "created": "2025-05-10T08:42:59.000Z",
        "updated": "2025-05-10T08:42:59.000Z",
        "resources": 0,
        "size": "4.99",
        "sizeFmt": "4.99 Ha.",
        "url": "https://www.ffm.vic.gov.au/bushfire-fuel-and-risk-management/planned-burning-in-victoria",
        "location": "2.11Km N Of Morwell"
      },
      "type": "Feature",
      "geometry": {
        "type": "Point",
        "coordinates": [
          146.4206398,
          -38.2142766
        ]
      }
    },
    {
      "properties": {
        "status": "Patrolled",
        "feedType": "incident",
        "sourceOrg": "VIC/DELWP",
        "sourceId": 3018827,
        "sourceFeed": "delwp-burns",
        "sourceTitle": "Batesford - Dog Rocks Reserve",
        "id": 3018827,
        "category1": "Planned Burn",
        "category2": "Planned Burn",
        "created": "2025-06-19T08:58:28.000Z",
        "updated": "2025-06-19T08:58:28.000Z",
        "resources": 0,
        "size": "25.98",
        "sizeFmt": "25.98 Ha.",
        "url": "https://www.ffm.vic.gov.au/bushfire-fuel-and-risk-management/planned-burning-in-victoria",
        "location": "1Km Sw Of Batesford"
      },
      "type": "Feature",
      "geometry": {
        "type": "Point",
        "coordinates": [
          144.2657616,
          -38.096636
        ]
      }
    },
    {
      "properties": {
        "status": "Patrolled",
        "feedType": "incident",
        "sourceOrg": "VIC/DELWP",
        "sourceId": 3018889,
        "sourceFeed": "delwp-burns",
        "sourceTitle": "Yellingbo - Macclesfield Road",
        "id": 3018889,
        "category1": "Planned Burn",
        "category2": "Planned Burn",
        "created": "2025-06-20T05:51:04.000Z",
        "updated": "2025-06-20T05:51:04.000Z",
        "resources": 0,
        "size": "7.47",
        "sizeFmt": "7.47 Ha.",
        "url": "https://www.ffm.vic.gov.au/bushfire-fuel-and-risk-management/planned-burning-in-victoria",
        "location": "4Km Sw Of Yellingbo"
      },
      "type": "Feature",
      "geometry": {
        "type": "Point",
        "coordinates": [
          145.4769576,
          -37.8592495
        ]
      }
    },
    {
      "properties": {
        "status": "In Progress",
        "feedType": "incident",
        "sourceOrg": "VIC/DELWP",
        "sourceId": 3019067,
        "sourceFeed": "delwp-burns",
        "sourceTitle": "Anglesea - Anglesea Heath",
        "id": 3019067,
        "category1": "Planned Burn",
        "category2": "Planned Burn",
        "created": "2025-06-20T02:16:13.000Z",
        "updated": "2025-06-20T02:16:13.000Z",
        "resources": 0,
        "size": "5953.06",
        "sizeFmt": "5953.06 Ha.",
        "url": "https://www.ffm.vic.gov.au/bushfire-fuel-and-risk-management/planned-burning-in-victoria",
        "location": "5Km W Of Anglesea"
      },
      "type": "Feature",
      "geometry": {
        "type": "Point",
        "coordinates": [
          144.1093758,
          -38.3879962
        ]
      }
    },
    {
      "properties": {
        "status": "Safe",
        "estaId": 120027015,
        "feedType": "incident",
        "source": "000",
        "sourceOrg": "VIC/FRV",
        "sourceId": "250619946",
        "sourceFeed": "mfb-incident",
        "sourceTitle": "Allambi St",
        "eventId": "250619946",
        "id": "ESTA:250619946",
        "suppress": false,
        "category1": "Fire",
        "category2": "Non Structure Fire",
        "created": "2025-06-20T23:16:03.000Z",
        "updated": "2025-06-20T23:16:03.000Z",
        "resources": 1,
        "location": "Allambi St, Ashwood",
        "mfbId": "250619946",
        "size": "Small",
        "sizeFmt": "Small"
      },
      "type": "Feature",
      "geometry": {
        "type": "Point",
        "coordinates": [
          145.09877148019572,
          -37.87270111420937
        ]
      }
    },
    {
      "properties": {
        "status": "Not Yet Under Control",
        "estaId": 120026965,
        "feedType": "incident",
        "source": "000",
        "sourceOrg": "VIC/CFA",
        "sourceId": 225828,
        "sourceFeed": "cfa-incident",
        "sourceTitle": "Potts Rd",
        "eventId": 250619929,
        "id": "ESTA:250619929",
        "suppress": false,
        "category1": "Fire",
        "category2": "Building Fire",
        "created": "2025-06-20T23:01:00.000Z",
        "updated": "2025-06-20T23:01:00.000Z",
        "resources": 3,
        "location": "Potts Rd, Langwarrin",
        "cfaId": 225828,
        "size": "Small",
        "sizeFmt": "Small"
      },
      "type": "Feature",
      "geometry": {
        "type": "Point",
        "coordinates": [
          145.20585946605422,
          -38.131600519521115
        ]
      }
    },
    {
      "properties": {
        "status": "Responding",
        "estaId": 120027104,
        "feedType": "incident",
        "source": "000",
        "sourceOrg": "VIC/CFA",
        "sourceId": 225830,
        "sourceFeed": "cfa-incident",
        "sourceTitle": "",
        "eventId": 250619975,
        "id": "ESTA:250619975",
        "suppress": false,
        "category1": "Accident / Rescue",
        "category2": "Road Accident",
        "created": "2025-06-20T23:17:00.000Z",
        "updated": "2025-06-20T23:17:00.000Z",
        "resources": 0,
        "location": "Narre Warren South",
        "cfaId": 225830,
        "size": "Small",
        "sizeFmt": "Small"
      },
      "type": "Feature",
      "geometry": {
        "type": "Point",
        "coordinates": [
          145.3010989366913,
          -38.05490261595274
        ]
      }
    },
    {
      "properties": {
        "status": "Responding",
        "estaId": 120027154,
        "feedType": "incident",
        "source": "000",
        "sourceOrg": "VIC/CFA",
        "sourceId": 225831,
        "sourceFeed": "cfa-incident",
        "sourceTitle": "Toorak Cl",
        "eventId": 250619985,
        "id": "ESTA:250619985",
        "suppress": false,
        "category1": "Accident / Rescue",
        "category2": "Road Accident",
        "created": "2025-06-20T23:21:00.000Z",
        "updated": "2025-06-20T23:21:00.000Z",
        "resources": 0,
        "location": "Toorak Cl, Narre Warren South",
        "cfaId": 225831,
        "size": "Small",
        "sizeFmt": "Small"
      },
      "type": "Feature",
      "geometry": {
        "type": "Point",
        "coordinates": [
          145.30248726075794,
          -38.05499477301895
        ]
      }
    },
    {
      "properties": {
        "status": "Responding",
        "estaId": 120027157,
        "feedType": "incident",
        "source": "000",
        "sourceOrg": "VIC/CFA",
        "sourceId": 225832,
        "sourceFeed": "cfa-incident",
        "sourceTitle": "Toorak Cl",
        "eventId": 250619986,
        "id": "ESTA:250619986",
        "suppress": false,
        "category1": "Accident / Rescue",
        "category2": "Road Accident",
        "created": "2025-06-20T23:22:00.000Z",
        "updated": "2025-06-20T23:22:00.000Z",
        "resources": 0,
        "location": "Toorak Cl, Narre Warren South",
        "cfaId": 225832,
        "size": "Small",
        "sizeFmt": "Small"
      },
      "type": "Feature",
      "geometry": {
        "type": "Point",
        "coordinates": [
          145.30235366258884,
          -38.05485766530086
        ]
      }
    },
    {
      "properties": {
        "status": "Safe",
        "estaId": 120026906,
        "feedType": "incident",
        "source": "000",
        "sourceOrg": "VIC/CFA",
        "sourceId": 225827,
        "sourceFeed": "cfa-incident",
        "sourceTitle": "Primrose St",
        "eventId": 250619917,
        "id": "ESTA:250619917",
        "suppress": false,
        "category1": "Fire",
        "category2": "Building Fire",
        "created": "2025-06-20T22:54:00.000Z",
        "updated": "2025-06-20T23:05:00.000Z",
        "resources": 0,
        "location": "Primrose St, Wendouree",
        "cfaId": 225827,
        "size": "Small",
        "sizeFmt": "Small"
      },
      "type": "Feature",
      "geometry": {
        "type": "Point",
        "coordinates": [
          143.82082221577943,
          -37.53153038320113
        ]
      }
    },
    {
      "properties": {
        "status": "Under Control",
        "estaId": 120027103,
        "feedType": "incident",
        "source": "000",
        "sourceOrg": "VIC/FRV",
        "sourceId": "250619974",
        "sourceFeed": "mfb-incident",
        "sourceTitle": "Narre Warren South",
        "eventId": "250619974",
        "id": "ESTA:250619974",
        "suppress": false,
        "category1": "Other",
        "category2": "Other",
        "created": "2025-06-20T23:25:17.000Z",
        "updated": "2025-06-20T23:25:17.000Z",
        "resources": 3,
        "location": "Narre Warren South, Narre Warren South",
        "cfaId": 225829,
        "size": "Small",
        "sizeFmt": "Small",
        "mfbId": "250619974"
      },
      "type": "Feature",
      "geometry": {
        "type": "Point",
        "coordinates": [
          145.30220586726102,
          -38.055173059516214
        ]
      }
    },
    {
      "properties": {
        "status": "Safe",
        "cfaId": 225825,
        "feedType": "incident",
        "sourceOrg": "VIC/CFA",
        "sourceId": 225825,
        "sourceFeed": "cfa-incident",
        "sourceTitle": "May Rd",
        "eventId": 250619847,
        "id": "ESTA:250619847",
        "category1": "Fire",
        "category2": "Other",
        "created": "2025-06-20T22:17:00.000Z",
        "updated": "2025-06-20T22:27:00.000Z",
        "resources": 0,
        "location": "May Rd, Lalor",
        "size": "Small",
        "sizeFmt": "Small"
      },
      "type": "Feature",
      "geometry": {
        "type": "Point",
        "coordinates": [
          145.01771652523502,
          -37.67302410980983
        ]
      }
    },
    {
      "properties": {
        "status": "Safe",
        "cfaId": 225826,
        "feedType": "incident",
        "sourceOrg": "VIC/CFA",
        "sourceId": 225826,
        "sourceFeed": "cfa-incident",
        "sourceTitle": "Croxton Dr",
        "eventId": 250619901,
        "id": "ESTA:250619901",
        "category1": "Fire",
        "category2": "Other",
        "created": "2025-06-20T22:48:00.000Z",
        "updated": "2025-06-20T23:18:00.000Z",
        "resources": 0,
        "location": "Croxton Dr, Kurunjang",
        "size": "Small",
        "sizeFmt": "Small"
      },
      "type": "Feature",
      "geometry": {
        "type": "Point",
        "coordinates": [
          144.60267564195678,
          -37.66123270712566
        ]
      }
    },
    {
      "properties": {
        "status": "Under Control",
        "mfbId": "250618171",
        "feedType": "incident",
        "sourceOrg": "VIC/FRV",
        "sourceId": "250618171",
        "sourceFeed": "mfb-incident",
        "sourceTitle": "Balmoral Cct",
        "id": "ESTA:250618171",
        "eventId": "250618171",
        "category1": "Fire",
        "category2": "Structure Fire",
        "created": "2025-06-19T11:34:10.000Z",
        "updated": "2025-06-19T11:34:10.000Z",
        "resources": 0,
        "size": "Small",
        "sizeFmt": "Small",
        "location": "Balmoral Cct, Sunbury"
      },
      "type": "Feature",
      "geometry": {
        "type": "Point",
        "coordinates": [
          144.71138808362127,
          -37.56743741968075
        ]
      }
    },
    {
      "properties": {
        "status": "Request For Assistance",
        "sesId": 570000,
        "feedType": "incident",
        "sourceOrg": "VIC/SES",
        "sourceId": 570000,
        "sourceFeed": "ses-incident",
        "sourceTitle": "Undefined",
        "eventId": 250651108,
        "id": "ESTA:250651108",
        "category1": "Flooding",
        "category2": "Flooding",
        "created": "2025-06-20T07:33:00.000Z",
        "updated": "2025-06-20T07:36:00.000Z",
        "resources": 0,
        "location": "St Kilda"
      },
      "type": "Feature",
      "geometry": {
        "type": "Point",
        "coordinates": [
          144.98262999570522,
          -37.860425157700725
        ]
      }
    }
  ],
  "properties": {
    "conditions": {
      "fdr": {
        "Mallee": "NO FORECAST",
        "Wimmera": "NO FORECAST",
        "South West": "NO FORECAST",
        "Northern Country": "NO FORECAST",
        "North Central": "NO FORECAST",
        "Central": "NO FORECAST",
        "North East": "NO FORECAST",
        "West and South Gippsland": "NO FORECAST",
        "East Gippsland": "NO FORECAST"
      },
      "tfb": {
        "East Gippsland": "NO - RESTRICTIONS MAY APPLY",
        "West and South Gippsland": "NO - RESTRICTIONS MAY APPLY",
        "North East": "NO - RESTRICTIONS MAY APPLY",
        "Central": "NO - RESTRICTIONS MAY APPLY",
        "North Central": "NO - RESTRICTIONS MAY APPLY",
        "Northern Country": "NO - RESTRICTIONS MAY APPLY",
        "South West": "NO - RESTRICTIONS MAY APPLY",
        "Wimmera": "NO - RESTRICTIONS MAY APPLY",
        "Mallee": "NO - RESTRICTIONS MAY APPLY"
      },
      "forecasts": [
        {
          "fdr": {
            "Mallee": "NO FORECAST",
            "Wimmera": "NO FORECAST",
            "South West": "NO FORECAST",
            "Northern Country": "NO FORECAST",
            "North Central": "NO FORECAST",
            "Central": "NO FORECAST",
            "North East": "NO FORECAST",
            "West and South Gippsland": "NO FORECAST",
            "East Gippsland": "NO FORECAST"
          },
          "tfb": {
            "East Gippsland": "NO - RESTRICTIONS MAY APPLY",
            "West and South Gippsland": "NO - RESTRICTIONS MAY APPLY",
            "North East": "NO - RESTRICTIONS MAY APPLY",
            "Central": "NO - RESTRICTIONS MAY APPLY",
            "North Central": "NO - RESTRICTIONS MAY APPLY",
            "Northern Country": "NO - RESTRICTIONS MAY APPLY",
            "South West": "NO - RESTRICTIONS MAY APPLY",
            "Wimmera": "NO - RESTRICTIONS MAY APPLY",
            "Mallee": "NO - RESTRICTIONS MAY APPLY"
          },
          "date": "2025-06-20T14:00:00.000Z",
          "heat": {
            "Mallee": "Not Declared",
            "Wimmera": "Not Declared",
            "Northern Country": "Not Declared",
            "North East": "Not Declared",
            "East Gippsland": "Not Declared",
            "West and South Gippsland": "Not Declared",
            "Central": "Not Declared",
            "North Central": "Not Declared",
            "South West": "Not Declared"
          },
          "asthma": {
            "Mallee": "None",
            "Wimmera": "None",
            "Northern Country": "None",
            "North East": "None",
            "East Gippsland": "None",
            "West and South Gippsland": "None",
            "Central": "None",
            "North Central": "None",
            "South West": "None"
          }
        },
        {
          "fdr": {
            "Mallee": "NO FORECAST",
            "Wimmera": "NO FORECAST",
            "South West": "NO FORECAST",
            "Northern Country": "NO FORECAST",
            "North Central": "NO FORECAST",
            "Central": "NO FORECAST",
            "North East": "NO FORECAST",
            "West and South Gippsland": "NO FORECAST",
            "East Gippsland": "NO FORECAST"
          },
          "tfb": {
            "East Gippsland": "NO - RESTRICTIONS MAY APPLY",
            "West and South Gippsland": "NO - RESTRICTIONS MAY APPLY",
            "North East": "NO - RESTRICTIONS MAY APPLY",
            "Central": "NO - RESTRICTIONS MAY APPLY",
            "North Central": "NO - RESTRICTIONS MAY APPLY",
            "Northern Country": "NO - RESTRICTIONS MAY APPLY",
            "South West": "NO - RESTRICTIONS MAY APPLY",
            "Wimmera": "NO - RESTRICTIONS MAY APPLY",
            "Mallee": "NO - RESTRICTIONS MAY APPLY"
          },
          "date": "2025-06-21T14:00:00.000Z",
          "heat": {
            "Mallee": "Not Declared",
            "Wimmera": "Not Declared",
            "Northern Country": "Not Declared",
            "North East": "Not Declared",
            "East Gippsland": "Not Declared",
            "West and South Gippsland": "Not Declared",
            "Central": "Not Declared",
            "North Central": "Not Declared",
            "South West": "Not Declared"
          },
          "asthma": {
            "Mallee": "None",
            "Wimmera": "None",
            "Northern Country": "None",
            "North East": "None",
            "East Gippsland": "None",
            "West and South Gippsland": "None",
            "Central": "None",
            "North Central": "None",
            "South West": "None"
          }
        },
        {
          "fdr": {
            "Mallee": "NO FORECAST",
            "Wimmera": "NO FORECAST",
            "South West": "NO FORECAST",
            "Northern Country": "NO FORECAST",
            "North Central": "NO FORECAST",
            "Central": "NO FORECAST",
            "North East": "NO FORECAST",
            "West and South Gippsland": "NO FORECAST",
            "East Gippsland": "NO FORECAST"
          },
          "tfb": {
            "East Gippsland": "NO - RESTRICTIONS MAY APPLY",
            "West and South Gippsland": "NO - RESTRICTIONS MAY APPLY",
            "North East": "NO - RESTRICTIONS MAY APPLY",
            "Central": "NO - RESTRICTIONS MAY APPLY",
            "North Central": "NO - RESTRICTIONS MAY APPLY",
            "Northern Country": "NO - RESTRICTIONS MAY APPLY",
            "South West": "NO - RESTRICTIONS MAY APPLY",
            "Wimmera": "NO - RESTRICTIONS MAY APPLY",
            "Mallee": "NO - RESTRICTIONS MAY APPLY"
          },
          "date": "2025-06-22T14:00:00.000Z",
          "heat": {
            "Mallee": "Not Declared",
            "Wimmera": "Not Declared",
            "Northern Country": "Not Declared",
            "North East": "Not Declared",
            "East Gippsland": "Not Declared",
            "West and South Gippsland": "Not Declared",
            "Central": "Not Declared",
            "North Central": "Not Declared",
            "South West": "Not Declared"
          },
          "asthma": {
            "Mallee": "None",
            "Wimmera": "None",
            "Northern Country": "None",
            "North East": "None",
            "East Gippsland": "None",
            "West and South Gippsland": "None",
            "Central": "None",
            "North Central": "None",
            "South West": "None"
          }
        },
        {
          "fdr": {
            "Mallee": "NO FORECAST",
            "Wimmera": "NO FORECAST",
            "South West": "NO FORECAST",
            "Northern Country": "NO FORECAST",
            "North Central": "NO FORECAST",
            "Central": "NO FORECAST",
            "North East": "NO FORECAST",
            "West and South Gippsland": "NO FORECAST",
            "East Gippsland": "NO FORECAST"
          },
          "tfb": {
            "East Gippsland": "NO - RESTRICTIONS MAY APPLY",
            "West and South Gippsland": "NO - RESTRICTIONS MAY APPLY",
            "North East": "NO - RESTRICTIONS MAY APPLY",
            "Central": "NO - RESTRICTIONS MAY APPLY",
            "North Central": "NO - RESTRICTIONS MAY APPLY",
            "Northern Country": "NO - RESTRICTIONS MAY APPLY",
            "South West": "NO - RESTRICTIONS MAY APPLY",
            "Wimmera": "NO - RESTRICTIONS MAY APPLY",
            "Mallee": "NO - RESTRICTIONS MAY APPLY"
          },
          "date": "2025-06-23T14:00:00.000Z",
          "heat": {
            "Mallee": "Not Declared",
            "Wimmera": "Not Declared",
            "Northern Country": "Not Declared",
            "North East": "Not Declared",
            "East Gippsland": "Not Declared",
            "West and South Gippsland": "Not Declared",
            "Central": "Not Declared",
            "North Central": "Not Declared",
            "South West": "Not Declared"
          }
        }
      ],
      "heat": {
        "Mallee": "Not Declared",
        "Wimmera": "Not Declared",
        "Northern Country": "Not Declared",
        "North East": "Not Declared",
        "East Gippsland": "Not Declared",
        "West and South Gippsland": "Not Declared",
        "Central": "Not Declared",
        "North Central": "Not Declared",
        "South West": "Not Declared"
      },
      "asthma": {
        "Mallee": "None",
        "Wimmera": "None",
        "Northern Country": "None",
        "North East": "None",
        "East Gippsland": "None",
        "West and South Gippsland": "None",
        "Central": "None",
        "North Central": "None",
        "South West": "None"
      }
    },
    "notices": [],
    "lastUpdated": "2025-06-20T23:26:05.659Z",
    "featureCount": 120
  }
}
