{
  "type": "FeatureCollection",
  "features": [
    {
      "properties": {
        "status": "Responding",
        "estaId": 120345002,
        "feedType": "incident",
        "source": "000",
        "sourceOrg": "VIC/CFA",
        "sourceId": 229101,
        "sourceFeed": "cfa-incident",
        "sourceTitle": "Acacia Rd",
        "eventId": 250713361,
        "id": "ESTA:250713361",
        "suppress": false,
        "category1": "Fire",
        "category2": "Building Fire",
        "created": "2025-07-17T07:20:00.000Z",
        "updated": "2025-07-17T07:20:00.000Z",
        "resources": 3,
        "location": "Acacia Rd, Hurstbridge",
        "cfaId": 229101,
        "size": "Small",
        "sizeFmt": "Small"
      },
      "type": "Feature",
      "geometry": {
        "type": "Point",
        "coordinates": [
          145.18722993130473,
          -37.630717942320835
        ]
      }
    },
    {
      "properties": {
        "status": "Request For Assistance",
        "estaId": 120345028,
        "feedType": "incident",
        "source": "SES STRM",
        "sourceOrg": "VIC/SES",
        "sourceId": 572206,
        "sourceFeed": "ses-incident",
        "sourceTitle": "Undefined",
        "eventId": 250751206,
        "id": "ESTA:250751206",
        "suppress": false,
        "category1": "Tree Down",
        "category2": "Tree Down",
        "created": "2025-07-17T07:22:00.000Z",
        "updated": "2025-07-17T07:22:00.000Z",
        "resources": 1,
        "location": "Vesper",
        "sesId": 572206
      },
      "type": "Feature",
      "geometry": {
        "type": "Point",
        "coordinates": [
          146.0610769397563,
          -37.88626986739092
        ]
      }
    },
    {
      "properties": {
        "status": "Responding",
        "estaId": 120345005,
        "feedType": "incident",
        "source": "000",
        "sourceOrg": "VIC/FRV",
        "sourceId": "250713362",
        "sourceFeed": "mfb-incident",
        "sourceTitle": "Capon St",
        "eventId": "250713362",
        "id": "ESTA:250713362",
        "suppress": false,
        "category1": "Fire",
        "category2": "Non Structure Fire",
        "created": "2025-07-17T07:22:27.000Z",
        "updated": "2025-07-17T07:22:27.000Z",
        "resources": 2,
        "location": "Capon St, Malvern East",
        "mfbId": "250713362",
        "size": "Small",
        "sizeFmt": "Small"
      },
      "type": "Feature",
      "geometry": {
        "type": "Point",
        "coordinates": [
          145.08698722777152,
          -37.88464820968035
        ]
      }
    },
    {
      "properties": {
        "status": "Complete",
        "estaId": 120344501,
        "feedType": "incident",
        "source": "000",
        "sourceOrg": "VIC/SES",
        "sourceId": 572203,
        "sourceFeed": "ses-incident",
        "sourceTitle": "Undefined",
        "eventId": 250751200,
        "id": "ESTA:250751200",
        "suppress": false,
        "category1": "Tree Down",
        "category2": "Tree Down",
        "created": "2025-07-17T06:39:00.000Z",
        "updated": "2025-07-17T07:24:00.000Z",
        "resources": 0,
        "location": "Laverton",
        "sesId": 572203
      },
      "type": "Feature",
      "geometry": {
        "type": "Point",
        "coordinates": [
          144.77327815253963,
          -37.85342452603039
        ]
      }
    },
    {
      "properties": {
        "status": "Request For Assistance",
        "estaId": 120345050,
        "feedType": "incident",
        "source": "000",
        "sourceOrg": "VIC/SES",
        "sourceId": 572207,
        "sourceFeed": "ses-incident",
        "sourceTitle": "Undefined",
        "eventId": 250713367,
        "id": "ESTA:250713367",
        "suppress": false,
        "category1": "Rescue",
        "category2": "Rescue Road Trap",
        "created": "2025-07-17T07:24:00.000Z",
        "updated": "2025-07-17T07:27:00.000Z",
        "resources": 3,
        "location": "Breakwater",
        "cfaId": 229103,
        "size": "Small",
        "sizeFmt": "Small",
        "mfbId": "250713367",
        "sesId": 572207
      },
      "type": "Feature",
      "geometry": {
        "type": "Point",
        "coordinates": [
          144.36757781268807,
          -38.17933221085979
        ]
      }
    },
    {
      "properties": {
        "status": "Responding",
        "estaId": 120345051,
        "feedType": "incident",
        "source": "000",
        "sourceOrg": "VIC/ESTA",
        "sourceId": 120345051,
        "sourceFeed": "esta-cad-event",
        "sourceTitle": "Breakwater",
        "eventId": "F250713368",
        "id": "ESTA:250713368",
        "suppress": false,
        "category1": "Other",
        "category2": "Other",
        "created": "2025-07-17T07:20:27.000Z",
        "updated": "2025-07-17T07:24:28.131Z",
        "resources": 0,
        "location": "Tucker St, Breakwater"
      },
      "type": "Feature",
      "geometry": {
        "type": "Point",
        "coordinates": [
          144.36717183510936,
          -38.18125384477172
        ]
      }
    },
    {
      "properties": {
        "status": "Safe",
        "estaId": 120344697,
        "feedType": "incident",
        "source": "000",
        "sourceOrg": "VIC/CFA",
        "sourceId": 229099,
        "sourceFeed": "cfa-incident",
        "sourceTitle": "",
        "eventId": 250713350,
        "id": "ESTA:250713350",
        "suppress": false,
        "category1": "Fire",
        "category2": "Other",
        "created": "2025-07-17T06:54:00.000Z",
        "updated": "2025-07-17T07:09:00.000Z",
        "resources": 1,
        "location": "Caralulup",
        "cfaId": 229099,
        "size": "Small",
        "sizeFmt": "Small"
      },
      "type": "Feature",
      "geometry": {
        "type": "Point",
        "coordinates": [
          143.6425515552517,
          -37.19617345548937
        ]
      }
    },
    {
      "properties": {
        "status": "Responding",
        "estaId": 120345074,
        "feedType": "incident",
        "source": "000",
        "sourceOrg": "VIC/CFA",
        "sourceId": 229104,
        "sourceFeed": "cfa-incident",
        "sourceTitle": "Armstrongs Rd",
        "eventId": 250713369,
        "id": "ESTA:250713369",
        "suppress": false,
        "category1": "Fire",
        "category2": "Bushfire",
        "created": "2025-07-17T07:27:00.000Z",
        "updated": "2025-07-17T07:27:00.000Z",
        "resources": 0,
        "location": "Armstrongs Rd, Porepunkah",
        "cfaId": 229104,
        "size": "Small",
        "sizeFmt": "Small"
      },
      "type": "Feature",
      "geometry": {
        "type": "Point",
        "coordinates": [
          146.91656622163657,
          -36.69661508946373
        ]
      }
    },
    {
      "properties": {
        "status": "Responding",
        "estaId": 120345095,
        "feedType": "incident",
        "source": "000",
        "sourceOrg": "VIC/FRV",
        "sourceId": "250713370",
        "sourceFeed": "mfb-incident",
        "sourceTitle": "Gladstone Park",
        "eventId": "250713370",
        "id": "ESTA:250713370",
        "suppress": false,
        "category1": "Other",
        "category2": "Other",
        "created": "2025-07-17T07:28:33.000Z",
        "updated": "2025-07-17T07:28:33.000Z",
        "resources": 1,
        "location": "Gladstone Park, Gladstone Park",
        "mfbId": "250713370",
        "size": "Small",
        "sizeFmt": "Small"
      },
      "type": "Feature",
      "geometry": {
        "type": "Point",
        "coordinates": [
          144.88941548147704,
          -37.70454357284552
        ]
      }
    },
    {
      "properties": {
        "status": "Responding",
        "estaId": 120345100,
        "feedType": "incident",
        "source": "000",
        "sourceOrg": "VIC/ESTA",
        "sourceId": 120345100,
        "sourceFeed": "esta-cad-event",
        "sourceTitle": "Westmeadows",
        "eventId": "F250713371",
        "id": "ESTA:250713371",
        "suppress": false,
        "category1": "Hazardous Material",
        "category2": "Hazardous Material",
        "created": "2025-07-17T07:27:34.000Z",
        "updated": "2025-07-17T07:28:50.973Z",
        "resources": 0,
        "location": "Westmeadows"
      },
      "type": "Feature",
      "geometry": {
        "type": "Point",
        "coordinates": [
          144.8819603774821,
          -37.68995686912657
        ]
      }
    },
    {
      "properties": {
        "status": "Under Control",
        "feedType": "incident",
        "sourceOrg": "NSW/RFS",
        "sourceId": "612042",
        "sourceFeed": "rfs-cap",
        "sourceTitle": "Bungarby",
        "id": "2025-07-17T10:42:00.0000000:612042",
        "category1": "Other",
        "category2": "Other Non-Urgent Alerts",
        "name": "Bungarby",
        "location": "Bungarby 2630",
        "created": "2025-07-17T10:42:00+10:00",
        "updated": "2025-07-17T10:42:00+10:00",
        "webHeadline": "Unknown",
        "url": "https://www.rfs.nsw.gov.au/fire-information/fires-near-me",
        "sizeFmt": [
          "0 ha"
        ]
      },
      "type": "Feature",
      "geometry": {
        "type": "Point",
        "coordinates": [
          148.987365723,
          -36.719497681
        ]
      }
    },
    {
      "properties": {
        "status": "Safe",
        "cfaId": 229094,
        "feedType": "incident",
        "sourceOrg": "VIC/CFA",
        "sourceId": 229094,
        "sourceFeed": "cfa-incident",
        "sourceTitle": "Cooper St",
        "eventId": 250713323,
        "id": "ESTA:250713323",
        "category1": "Accident / Rescue",
        "category2": "Road Accident",
        "created": "2025-07-17T06:22:00.000Z",
        "updated": "2025-07-17T07:04:00.000Z",
        "resources": 0,
        "location": "Cooper St, Epping",
        "size": "Small",
        "sizeFmt": "Small"
      },
      "type": "Feature",
      "geometry": {
        "type": "Point",
        "coordinates": [
          145.02130891396453,
          -37.651743936218494
        ]
      }
    },
    {
      "properties": {
        "status": "Safe",
        "cfaId": 229096,
        "feedType": "incident",
        "sourceOrg": "VIC/CFA",
        "sourceId": 229096,
        "sourceFeed": "cfa-incident",
        "sourceTitle": "",
        "eventId": 250713331,
        "id": "ESTA:250713331",
        "category1": "Fire",
        "category2": "Bushfire",
        "created": "2025-07-17T06:35:00.000Z",
        "updated": "2025-07-17T07:05:00.000Z",
        "resources": 2,
        "location": "Loch Sport",
        "size": "Small",
        "sizeFmt": "Small"
      },
      "type": "Feature",
      "geometry": {
        "type": "Point",
        "coordinates": [
          147.56841010930583,
          -38.05764169005171
        ]
      }
    },
    {
      "properties": {
        "status": "Safe",
        "cfaId": 229098,
        "feedType": "incident",
        "sourceOrg": "VIC/CFA",
        "sourceId": 229098,
        "sourceFeed": "cfa-incident",
        "sourceTitle": "The Promenade -",
        "eventId": 250713347,
        "id": "ESTA:250713347",
        "category1": "Other",
        "category2": "Other",
        "created": "2025-07-17T06:51:00.000Z",
        "updated": "2025-07-17T07:11:00.000Z",
        "resources": 0,
        "location": "The Promenade -, Narre Warren South",
        "size": "Small",
        "sizeFmt": "Small"
      },
      "type": "Feature",
      "geometry": {
        "type": "Point",
        "coordinates": [
          145.30902180384075,
          -38.067696566281924
        ]
      }
    },
    {
      "properties": {
        "status": "Safe",
        "cfaId": 229097,
        "feedType": "incident",
        "sourceOrg": "VIC/FRV",
        "sourceId": "250713334",
        "sourceFeed": "mfb-incident",
        "sourceTitle": "Produce Dr",
        "eventId": "250713334",
        "id": "ESTA:250713334",
        "category1": "Other",
        "category2": "Other",
        "created": "2025-07-17T07:19:14.000Z",
        "updated": "2025-07-17T07:19:14.000Z",
        "resources": 3,
        "location": "Produce Dr, Dandenong South",
        "size": "Small",
        "sizeFmt": "Small",
        "mfbId": "250713334"
      },
      "type": "Feature",
      "geometry": {
        "type": "Point",
        "coordinates": [
          145.22064309283533,
          -38.037349941976004
        ]
      }
    },
    {
      "properties": {
        "status": "Safe",
        "cfaId": 229102,
        "feedType": "incident",
        "sourceOrg": "VIC/CFA",
        "sourceId": 229102,
        "sourceFeed": "cfa-incident",
        "sourceTitle": "",
        "eventId": 250713366,
        "id": "ESTA:250713366",
        "category1": "Other",
        "category2": "Other",
        "created": "2025-07-17T07:24:00.000Z",
        "updated": "2025-07-17T07:28:00.000Z",
        "resources": 0,
        "location": "Dean",
        "size": "Small",
        "sizeFmt": "Small"
      },
      "type": "Feature",
      "geometry": {
        "type": "Point",
        "coordinates": [
          143.9802335840269,
          -37.443129430921445
        ]
      }
    },
    {
      "properties": {
        "status": "Under Control",
        "mfbId": "250713336",
        "feedType": "incident",
        "sourceOrg": "VIC/FRV",
        "sourceId": "250713336",
        "sourceFeed": "mfb-incident",
        "sourceTitle": "Yarraville",
        "id": "ESTA:250713336",
        "eventId": "250713336",
        "category1": "Other",
        "category2": "Other",
        "created": "2025-07-17T07:05:48.000Z",
        "updated": "2025-07-17T07:05:48.000Z",
        "resources": 1,
        "size": "Small",
        "sizeFmt": "Small",
        "location": "Yarraville, Yarraville"
      },
      "type": "Feature",
      "geometry": {
        "type": "Point",
        "coordinates": [
          144.88088973920404,
          -37.825335553542
        ]
      }
    },
    {
      "properties": {
        "status": "Under Control",
        "mfbId": "250713255",
        "feedType": "incident",
        "sourceOrg": "VIC/FRV",
        "sourceId": "250713255",
        "sourceFeed": "mfb-incident",
        "sourceTitle": "Ardcloney Dr",
        "id": "ESTA:250713255",
        "eventId": "250713255",
        "category1": "Other",
        "category2": "Other",
        "created": "2025-07-17T05:25:14.000Z",
        "updated": "2025-07-17T05:25:14.000Z",
        "resources": 1,
        "size": "Small",
        "sizeFmt": "Small",
        "location": "Ardcloney Dr, Sunbury"
      },
      "type": "Feature",
      "geometry": {
        "type": "Point",
        "coordinates": [
          144.73337059886833,
          -37.57755362967293
        ]
      }
    },
    {
      "properties": {
        "status": "Under Control",
        "mfbId": "250713333",
        "feedType": "incident",
        "sourceOrg": "VIC/FRV",
        "sourceId": "250713333",
        "sourceFeed": "mfb-incident",
        "sourceTitle": "Laverton",
        "id": "ESTA:250713333",
        "eventId": "250713333",
        "category1": "Other",
        "category2": "Other",
        "created": "2025-07-17T06:50:20.000Z",
        "updated": "2025-07-17T06:50:20.000Z",
        "resources": 1,
        "size": "Small",
        "sizeFmt": "Small",
        "location": "Laverton, Laverton"
      },
      "type": "Feature",
      "geometry": {
        "type": "Point",
        "coordinates": [
          144.77328116873687,
          -37.853417773163315
        ]
      }
    },
    {
      "properties": {
        "status": "Under Control",
        "mfbId": "250713358",
        "feedType": "incident",
        "sourceOrg": "VIC/FRV",
        "sourceId": "250713358",
        "sourceFeed": "mfb-incident",
        "sourceTitle": "Princes Hwy",
        "id": "ESTA:250713358",
        "eventId": "250713358",
        "category1": "Other",
        "category2": "Other",
        "created": "2025-07-17T07:26:44.000Z",
        "updated": "2025-07-17T07:26:44.000Z",
        "resources": 2,
        "size": "Small",
        "sizeFmt": "Small",
        "location": "Princes Hwy, Springvale"
      },
      "type": "Feature",
      "geometry": {
        "type": "Point",
        "coordinates": [
          145.1536075487795,
          -37.93144988870793
        ]
      }
    },
    {
      "properties": {
        "status": "Safe",
        "mfbId": "250713354",
        "feedType": "incident",
        "sourceOrg": "VIC/FRV",
        "sourceId": "250713354",
        "sourceFeed": "mfb-incident",
        "sourceTitle": "South Gippsland Hwy",
        "id": "ESTA:250713354",
        "eventId": "250713354",
        "category1": "Other",
        "category2": "Other",
        "created": "2025-07-17T07:24:13.000Z",
        "updated": "2025-07-17T07:24:13.000Z",
        "resources": 1,
        "size": "Small",
        "sizeFmt": "Small",
        "location": "South Gippsland Hwy, Cranbourne"
      },
      "type": "Feature",
      "geometry": {
        "type": "Point",
        "coordinates": [
          145.28173750517374,
          -38.10247483815194
        ]
      }
    },
    {
      "properties": {
        "status": "Under Control",
        "mfbId": "250713301",
        "feedType": "incident",
        "sourceOrg": "VIC/FRV",
        "sourceId": "250713301",
        "sourceFeed": "mfb-incident",
        "sourceTitle": "Reservoir",
        "id": "ESTA:250713301",
        "eventId": "250713301",
        "category1": "Other",
        "category2": "Other",
        "created": "2025-07-17T06:17:16.000Z",
        "updated": "2025-07-17T06:17:16.000Z",
        "resources": 1,
        "size": "Small",
        "sizeFmt": "Small",
        "location": "Reservoir, Reservoir"
      },
      "type": "Feature",
      "geometry": {
        "type": "Point",
        "coordinates": [
          145.00066901478718,
          -37.693854135894256
        ]
      }
    },
    {
      "properties": {
        "status": "Under Control",
        "mfbId": "250713356",
        "feedType": "incident",
        "sourceOrg": "VIC/FRV",
        "sourceId": "250713356",
        "sourceFeed": "mfb-incident",
        "sourceTitle": "West Gate Fwy",
        "id": "ESTA:250713356",
        "eventId": "250713356",
        "category1": "Other",
        "category2": "Other",
        "created": "2025-07-17T07:09:40.000Z",
        "updated": "2025-07-17T07:09:40.000Z",
        "resources": 1,
        "size": "Small",
        "sizeFmt": "Small",
        "location": "West Gate Fwy, Spotswood"
      },
      "type": "Feature",
      "geometry": {
        "type": "Point",
        "coordinates": [
          144.88847730423285,
          -37.825496013897386
        ]
      }
    },
    {
      "properties": {
        "status": "On Scene",
        "sesId": 572193,
        "feedType": "incident",
        "sourceOrg": "VIC/SES",
        "sourceId": 572193,
        "sourceFeed": "ses-incident",
        "sourceTitle": "Undefined",
        "eventId": 250751192,
        "id": "ESTA:250751192",
        "category1": "Tree Down",
        "category2": "Tree Down",
        "created": "2025-07-17T04:04:00.000Z",
        "updated": "2025-07-17T05:14:00.000Z",
        "resources": 1,
        "location": "Tarra Valley"
      },
      "type": "Feature",
      "geometry": {
        "type": "Point",
        "coordinates": [
          146.5360612824258,
          -38.44556339905854
        ]
      }
    },
    {
      "properties": {
        "status": "Request For Assistance",
        "sesId": 572205,
        "feedType": "incident",
        "sourceOrg": "VIC/SES",
        "sourceId": 572205,
        "sourceFeed": "ses-incident",
        "sourceTitle": "Undefined",
        "eventId": 250751202,
        "id": "ESTA:250751202",
        "category1": "Tree Down",
        "category2": "Tree Down",
        "created": "2025-07-17T06:49:00.000Z",
        "updated": "2025-07-17T06:50:00.000Z",
        "resources": 1,
        "location": "Vesper"
      },
      "type": "Feature",
      "geometry": {
        "type": "Point",
        "coordinates": [
          146.0839174176801,
          -37.88581894059181
        ]
      }
    },
    {
      "properties": {
        "status": "Request For Assistance",
        "sesId": 572204,
        "feedType": "incident",
        "sourceOrg": "VIC/SES",
        "sourceId": 572204,
        "sourceFeed": "ses-incident",
        "sourceTitle": "Undefined",
        "eventId": 250751201,
        "id": "ESTA:250751201",
        "category1": "Tree Down",
        "category2": "Tree Down",
        "created": "2025-07-17T06:46:00.000Z",
        "updated": "2025-07-17T06:50:00.000Z",
        "resources": 1,
        "location": "Vesper"
      },
      "type": "Feature",
      "geometry": {
        "type": "Point",
        "coordinates": [
          146.06788680648222,
          -37.88642312911827
        ]
      }
    },
    {
      "properties": {
        "status": "Request For Assistance",
        "sesId": 572202,
        "feedType": "incident",
        "sourceOrg": "VIC/SES",
        "sourceId": 572202,
        "sourceFeed": "ses-incident",
        "sourceTitle": "Undefined",
        "eventId": 250751199,
        "id": "ESTA:250751199",
        "category1": "Tree Down",
        "category2": "Tree Down",
        "created": "2025-07-17T06:28:00.000Z",
        "updated": "2025-07-17T06:50:00.000Z",
        "resources": 1,
        "location": "Vesper"
      },
      "type": "Feature",
      "geometry": {
        "type": "Point",
        "coordinates": [
          146.05047275356245,
          -37.88581528306525
        ]
      }
    }
  ],
  "properties": {
    "conditions": {
      "fdr": {
        "Mallee": "NO FORECAST",
        "Wimmera": "NO FORECAST",
        "South West": "NO FORECAST",
        "Northern Country": "NO FORECAST",
        "North Central": "NO FORECAST",
        "Central": "NO FORECAST",
        "North East": "NO FORECAST",
        "West and South Gippsland": "NO FORECAST",
        "East Gippsland": "NO FORECAST"
      },
      "tfb": {
        "East Gippsland": "NO - RESTRICTIONS MAY APPLY",
        "West and South Gippsland": "NO - RESTRICTIONS MAY APPLY",
        "North East": "NO - RESTRICTIONS MAY APPLY",
        "Central": "NO - RESTRICTIONS MAY APPLY",
        "North Central": "NO - RESTRICTIONS MAY APPLY",
        "Northern Country": "NO - RESTRICTIONS MAY APPLY",
        "South West": "NO - RESTRICTIONS MAY APPLY",
        "Wimmera": "NO - RESTRICTIONS MAY APPLY",
        "Mallee": "NO - RESTRICTIONS MAY APPLY"
      },
      "forecasts": [
        {
          "fdr": {
            "Mallee": "NO FORECAST",
            "Wimmera": "NO FORECAST",
            "South West": "NO FORECAST",
            "Northern Country": "NO FORECAST",
            "North Central": "NO FORECAST",
            "Central": "NO FORECAST",
            "North East": "NO FORECAST",
            "West and South Gippsland": "NO FORECAST",
            "East Gippsland": "NO FORECAST"
          },
          "tfb": {
            "East Gippsland": "NO - RESTRICTIONS MAY APPLY",
            "West and South Gippsland": "NO - RESTRICTIONS MAY APPLY",
            "North East": "NO - RESTRICTIONS MAY APPLY",
            "Central": "NO - RESTRICTIONS MAY APPLY",
            "North Central": "NO - RESTRICTIONS MAY APPLY",
            "Northern Country": "NO - RESTRICTIONS MAY APPLY",
            "South West": "NO - RESTRICTIONS MAY APPLY",
            "Wimmera": "NO - RESTRICTIONS MAY APPLY",
            "Mallee": "NO - RESTRICTIONS MAY APPLY"
          },
          "date": "2025-07-16T14:00:00.000Z",
          "heat": {
            "Mallee": "Not Declared",
            "Wimmera": "Not Declared",
            "Northern Country": "Not Declared",
            "North East": "Not Declared",
            "East Gippsland": "Not Declared",
            "West and South Gippsland": "Not Declared",
            "Central": "Not Declared",
            "North Central": "Not Declared",
            "South West": "Not Declared"
          },
          "asthma": {
            "Mallee": "None",
            "Wimmera": "None",
            "Northern Country": "None",
            "North East": "None",
            "East Gippsland": "None",
            "West and South Gippsland": "None",
            "Central": "None",
            "North Central": "None",
            "South West": "None"
          }
        },
        {
          "fdr": {
            "Mallee": "NO FORECAST",
            "Wimmera": "NO FORECAST",
            "South West": "NO FORECAST",
            "Northern Country": "NO FORECAST",
            "North Central": "NO FORECAST",
            "Central": "NO FORECAST",
            "North East": "NO FORECAST",
            "West and South Gippsland": "NO FORECAST",
            "East Gippsland": "NO FORECAST"
          },
          "tfb": {
            "East Gippsland": "NO - RESTRICTIONS MAY APPLY",
            "West and South Gippsland": "NO - RESTRICTIONS MAY APPLY",
            "North East": "NO - RESTRICTIONS MAY APPLY",
            "Central": "NO - RESTRICTIONS MAY APPLY",
            "North Central": "NO - RESTRICTIONS MAY APPLY",
            "Northern Country": "NO - RESTRICTIONS MAY APPLY",
            "South West": "NO - RESTRICTIONS MAY APPLY",
            "Wimmera": "NO - RESTRICTIONS MAY APPLY",
            "Mallee": "NO - RESTRICTIONS MAY APPLY"
          },
          "date": "2025-07-17T14:00:00.000Z",
          "heat": {
            "Mallee": "Not Declared",
            "Wimmera": "Not Declared",
            "Northern Country": "Not Declared",
            "North East": "Not Declared",
            "East Gippsland": "Not Declared",
            "West and South Gippsland": "Not Declared",
            "Central": "Not Declared",
            "North Central": "Not Declared",
            "South West": "Not Declared"
          },
          "asthma": {
            "Mallee": "None",
            "Wimmera": "None",
            "Northern Country": "None",
            "North East": "None",
            "East Gippsland": "None",
            "West and South Gippsland": "None",
            "Central": "None",
            "North Central": "None",
            "South West": "None"
          }
        },
        {
          "fdr": {
            "Mallee": "NO FORECAST",
            "Wimmera": "NO FORECAST",
            "South West": "NO FORECAST",
            "Northern Country": "NO FORECAST",
            "North Central": "NO FORECAST",
            "Central": "NO FORECAST",
            "North East": "NO FORECAST",
            "West and South Gippsland": "NO FORECAST",
            "East Gippsland": "NO FORECAST"
          },
          "tfb": {
            "East Gippsland": "NO - RESTRICTIONS MAY APPLY",
            "West and South Gippsland": "NO - RESTRICTIONS MAY APPLY",
            "North East": "NO - RESTRICTIONS MAY APPLY",
            "Central": "NO - RESTRICTIONS MAY APPLY",
            "North Central": "NO - RESTRICTIONS MAY APPLY",
            "Northern Country": "NO - RESTRICTIONS MAY APPLY",
            "South West": "NO - RESTRICTIONS MAY APPLY",
            "Wimmera": "NO - RESTRICTIONS MAY APPLY",
            "Mallee": "NO - RESTRICTIONS MAY APPLY"
          },
          "date": "2025-07-18T14:00:00.000Z",
          "heat": {
            "Mallee": "Not Declared",
            "Wimmera": "Not Declared",
            "Northern Country": "Not Declared",
            "North East": "Not Declared",
            "East Gippsland": "Not Declared",
            "West and South Gippsland": "Not Declared",
            "Central": "Not Declared",
            "North Central": "Not Declared",
            "South West": "Not Declared"
          },
          "asthma": {
            "Mallee": "None",
            "Wimmera": "None",
            "Northern Country": "None",
            "North East": "None",
            "East Gippsland": "None",
            "West and South Gippsland": "None",
            "Central": "None",
            "North Central": "None",
            "South West": "None"
          }
        },
        {
          "fdr": {
            "Mallee": "NO FORECAST",
            "Wimmera": "NO FORECAST",
            "South West": "NO FORECAST",
            "Northern Country": "NO FORECAST",
            "North Central": "NO FORECAST",
            "Central": "NO FORECAST",
            "North East": "NO FORECAST",
            "West and South Gippsland": "NO FORECAST",
            "East Gippsland": "NO FORECAST"
          },
          "tfb": {
            "East Gippsland": "NO - RESTRICTIONS MAY APPLY",
            "West and South Gippsland": "NO - RESTRICTIONS MAY APPLY",
            "North East": "NO - RESTRICTIONS MAY APPLY",
            "Central": "NO - RESTRICTIONS MAY APPLY",
            "North Central": "NO - RESTRICTIONS MAY APPLY",
            "Northern Country": "NO - RESTRICTIONS MAY APPLY",
            "South West": "NO - RESTRICTIONS MAY APPLY",
            "Wimmera": "NO - RESTRICTIONS MAY APPLY",
            "Mallee": "NO - RESTRICTIONS MAY APPLY"
          },
          "date": "2025-07-19T14:00:00.000Z",
          "heat": {
            "Mallee": "Not Declared",
            "Wimmera": "Not Declared",
            "Northern Country": "Not Declared",
            "North East": "Not Declared",
            "East Gippsland": "Not Declared",
            "West and South Gippsland": "Not Declared",
            "Central": "Not Declared",
            "North Central": "Not Declared",
            "South West": "Not Declared"
          }
        }
      ],
      "heat": {
        "Mallee": "Not Declared",
        "Wimmera": "Not Declared",
        "Northern Country": "Not Declared",
        "North East": "Not Declared",
        "East Gippsland": "Not Declared",
        "West and South Gippsland": "Not Declared",
        "Central": "Not Declared",
        "North Central": "Not Declared",
        "South West": "Not Declared"
      },
      "asthma": {
        "Mallee": "None",
        "Wimmera": "None",
        "Northern Country": "None",
        "North East": "None",
        "East Gippsland": "None",
        "West and South Gippsland": "None",
        "Central": "None",
        "North Central": "None",
        "South West": "None"
      }
    },
    "notices": [],
    "lastUpdated": "2025-07-17T07:29:40.552Z",
    "featureCount": 27
  }
}
